fmt_tests.py
setup.py
solfmt.py
solfmt.egg-info/PKG-INFO
solfmt.egg-info/SOURCES.txt
solfmt.egg-info/dependency_links.txt
solfmt.egg-info/entry_points.txt
solfmt.egg-info/top_level.txt