Metadata-Version: 1.1
Name: solfmt
Version: 0.0.7
Summary: Solfmt a code formatter for Solidity
Home-page: UNKNOWN
Author: Alex Myasoedov
Author-email: msoedov@gmail.com
License: MIT
Platform: UNKNOWN
Classifier: Programming Language :: Python
Classifier: Programming Language :: Python :: 2.7
Classifier: Programming Language :: Python :: 3.3
Classifier: Programming Language :: Python :: 3.4
Classifier: Programming Language :: Python :: 3.5
Classifier: Programming Language :: Python :: 3.6
